{
    "es": {
        "coordenadas": "Coordenadas",
        "titulo": "Nombre",
        "archivo": "Carga la imagen / Documentación",
        "descripcion": "Descripción",
        "instructivo-movil":"Mantené presionada la pantalla del mapa para agregar contenido",
        "instructivo-computadora":"Hacé click derecho en el mapa para agregar contenido",
		"volver":"< Volver",
		"enviar":"Enviar",
		"nation":"Pueblo Nación",
		"contenido":"¿De qué trata el contenido?",
		"contenido-persona":"Persona",
		"contenido-artesania":"Artesanía",
		"contenido-danza":"Danza",
		"contenido-tradicion":"Tradición",
		"contenido-festival":"Festival",
		"contenido-pintura":"Pintura",
		"contenido-mural":"Mural",
		"contenido-dibujo":"Dibujo",
		"contenido-planta":"Planta/s",
		"contenido-institucion":"Institución",
		"contenido-organizacion":"Organización",
		"contenido-personas":"Grupo de personas",
		"contenido-vivienda":"Vivienda",
		"contenido-escultura":"Escultura",
		"contenido-tejido":"Tejido",
		"contenido-juegos":"Juegos",
		"contenido-culto":"Culto",
		"contenido-musica":"Música",
		"contenido-lugar":"Sitio o lugar",
		"contenido-espacio":"Espacio natural",
		"contenido-investigacion":"Investigación científica",
		"contenido-material-didactico":"Material didáctico",
		"contenido-animal":"Animal/es"
    },
    "qom": {
        "coordenadas": "Nchiguiña-lma’",
        "titulo": "L’enaxat, nlonaxat, nlotaguet.",
        "archivo": "ʼayoxoxoshiguem na lqui̕i nam ʼarʼoatac / Lmalatepi",
        "descripcion": "Nachaxanataxanaxac",
        "instructivo-movil":"apataxañe añe negaxaijte maye paʼayague na oic ỹaqto̕ ishet ra aqotnehuo ca rallaxaic arʼonatac.",
        "instructivo-computadora":"Apataxañe añe negaxaijte maye paʼayague na oic ỹaqto̕ ishet ra aqotnehuo ca rallaxaic arʼonatac.",
		"volver":"< ʼan ñe ʼeguelaxat",
		"enviar":"ʼahuamaq",
		"nation":"Yi noỹic/ na lauo’",
		"contenido":"¿De qué trata el contenido?",
		"contenido-persona":"Persona",
		"contenido-artesania":"Artesanía",
		"contenido-danza":"Danza",
		"contenido-tradicion":"Tradición",
		"contenido-festival":"Festival",
		"contenido-pintura":"Pintura",
		"contenido-mural":"Mural",
		"contenido-dibujo":"Dibujo",
		"contenido-planta":"Planta/s",
		"contenido-institucion":"Institución",
		"contenido-organizacion":"Organización",
		"contenido-personas":"Grupo de personas",
		"contenido-vivienda":"Vivienda",
		"contenido-escultura":"Escultura",
		"contenido-tejido":"Tejido",
		"contenido-juegos":"Juegos",
		"contenido-culto":"Culto",
		"contenido-musica":"Música",
		"contenido-lugar":"Sitio o lugar",
		"contenido-espacio":"Espacio natural",
		"contenido-investigacion":"Investigación científica",
		"contenido-material-didactico":"Material didáctico",
		"contenido-animal":"Animal/es"
    },
    "moqoit": {
        "coordenadas": "Laloqote>",
        "titulo": "Na>maq Leenaxat",
        "archivo": "Naqairishiguim nqui>i / Nerqaipi naneresañi",
        "descripcion": "Nachaxanatec",
        "instructivo-movil":"Pataqaisañi nata> nachaxanatec >laua lomalate quiyim lecqajñiro ro>ueenachigui.",
        "instructivo-computadora":"Ñitetegue click quena nimiitaxanaxac loicsec quena >laua lomalate quiyim lecqajñiro na>maq no>ueenatec hueetaugui.",
		"volver":"< Qaiqoshaxan",
		"enviar":"Qaila>a",
		"nation":"Nauo>/Chicqochigui",
		"contenido":"¿ÑIGUE> RELOQO’TEGUE NATAXARE NEDAXASET?",
		"contenido-persona":"QOM",
		"contenido-artesania":"NO>XONEC",
		"contenido-danza":"NASOTAXAC",
		"contenido-tradicion":">UEENATAXAC",
		"contenido-festival":"NEMAQACHIC",
		"contenido-pintura":"SHILAXAT",
		"contenido-mural":">IIMEC LAHI",
		"contenido-dibujo":"NADENQATEC",
		"contenido-planta":"NANEC/NANECSERIPI",
		"contenido-institucion":"NO>UEENATAXANAXAQUI",
		"contenido-organizacion":"Organización",
		"contenido-personas":"QOMYIPI",
		"contenido-vivienda":">IIMEC",
		"contenido-escultura":"NADENQATEC",
		"contenido-tejido":"NO>XONEC NAQALETENEC",
		"contenido-juegos":"NISHIQUIAXAC/NEUALLAXAQ",
		"contenido-culto":"NO>UEENAXANAXAQ",
		"contenido-musica":"NEVIIGAXANAQ",
		"contenido-lugar":"NOMA>/ NQA>XANQ>",
		"contenido-espacio":"NOUOOQO>",
		"contenido-investigacion":"PAXAGUINAXAQA> LOMA> NA> PAXAGUINAXAIC",
		"contenido-material-didactico":"Material didáctico",
		"contenido-animal":"ISECỸAC/ISERIPI"
    },
    "wichi": {
        "coordenadas": "Om kalelhojh mak tojh lhenlhi",
        "titulo": "Tolesainek-hi",
        "archivo": "Thathu apeyak / Achemet",
        "descripcion": "wichi",
        "instructivo-movil":"Tshokpe mapa tojh ihi pantalla che lathek latathu ahanyajh",
        "instructivo-computadora":"Che lathathu ahanyajh tojha watlok lhenlhi click tojh ihi afwumkat, tojha ihi mapa",
		"volver":"< Akhey",
		"enviar":"Thattshi",
		"nation":"Aw’etes/Nación",
		"contenido":"¿Athep yomey mak tojh hana?",
		"contenido-persona":"To-elh",
		"contenido-artesania":"Toñhiy",
		"contenido-danza":"Takatin",
		"contenido-tradicion":"Tokheyis",
		"contenido-festival":"Iwukhojhyajha",
		"contenido-pintura":"Pintura",
		"contenido-mural":"Mural",
		"contenido-dibujo":"Totenek",
		"contenido-planta":"Tokos",
		"contenido-institucion":"Tochemetw’et",
		"contenido-organizacion":"Lhiwalhathen",
		"contenido-personas":"Toñhojfwas",
		"contenido-vivienda":"Hep",
		"contenido-escultura":"Tolhenek",
		"contenido-tejido":"Tolhenek",
		"contenido-juegos":"Tokuyek",
		"contenido-culto":"Lhawuk-w'et",
		"contenido-musica":"Tositek",
		"contenido-lugar":"Tow'etes",
		"contenido-espacio":"Espacio natural",
		"contenido-investigacion":"Investigación científica",
		"contenido-material-didactico":"Material didáctico",
		"contenido-animal":"Tshotoy"
    }
}